<?xml version="1.0" encoding="UTF-8"?>
<Mappings>
	<Mapping>
		<Event>VolumeInc</Event>
		<Command>irsend SEND_ONCE TEAC_H300 KEY_VOLUMEUP</Command>
		<!-- Command>notepad.exe UP</Command -->
	</Mapping>

	<Mapping>
		<Event>VolumeDec</Event>
		<Command>irsend SEND_ONCE TEAC_H300 KEY_VOLUMEDOWN</Command>
		<!-- Command>notepad.exe DOWN</Command -->
	</Mapping>

	<Mapping>
		<Event>SourceChanged</Event>
		<Name>DAB Radio</Name>
		<Command>irsend SEND_ONCE TEAC_H300 KEY_KP1</Command>
	</Mapping>

	<Mapping>
		<Event>SourceChanged</Event>
		<Name>Home PC</Name>
		<Command>irsend SEND_ONCE TEAC_H300 KEY_KP1</Command>
	</Mapping>

	<Mapping>
		<Event>SourceChanged</Event>
		<Name>iPod</Name>
		<Command>irsend SEND_ONCE TEAC_H300 KEY_KP3</Command>
	</Mapping>

	<Mapping>
		<Event>SourceChanged</Event>
		<Name>Laptop</Name>
		<Command>irsend SEND_ONCE TEAC_H300 KEY_KP4</Command>
	</Mapping>

	<Mapping>
		<Event>SourceChanged</Event>
		<Name>PlayList</Name>
		<Command>irsend SEND_ONCE TEAC_H300 KEY_KP3</Command>
	</Mapping>
	
	<Mapping>
		<Event>SourceChanged</Event>
		<Name>Radio</Name>
		<Command>irsend SEND_ONCE TEAC_H300 KEY_KP3</Command>
	</Mapping>
	
	<Mapping>
		<Event>StandbyChanged</Event>
		<Name>true</Name>
		<Command>irsend SEND_ONCE TEAC_H300 KEY_POWER2</Command>
	</Mapping>
	
	<Mapping>
		<Event>StandbyChanged</Event>
		<Name>false</Name>
		<Command>irsend SEND_ONCE TEAC_H300 KEY_POWER</Command>
	</Mapping>

</Mappings>